{"version":1,"resource":"file:///home/z/.mozilla/firefox/00dolo9h.default-release/smart-fox/scripts/tabs.js","entries":[{"id":"puXW.js","timestamp":1705289193686},{"id":"OkVS.js","timestamp":1705289247814},{"id":"YR7c.js","timestamp":1705289346114},{"id":"p5lK.js","timestamp":1705289524278},{"id":"Q3d8.js","timestamp":1705289787582},{"id":"xfhy.js","timestamp":1705290219294},{"id":"3SFF.js","timestamp":1705290668762},{"id":"aacc.js","timestamp":1705290710510},{"id":"V91U.js","timestamp":1705290734486},{"id":"YRQs.js","timestamp":1705290947826},{"id":"Qzom.js","timestamp":1705291057290},{"id":"GQVr.js","timestamp":1705291077086},{"id":"yf4p.js","timestamp":1705292158278},{"id":"CLcI.js","timestamp":1705292253338},{"id":"QhVJ.js","timestamp":1705292566118},{"id":"ixeW.js","timestamp":1705292671646}]}